papermc_plugin_manager/__init__.py
papermc_plugin_manager/__main__.py
papermc_plugin_manager/config.py
papermc_plugin_manager/connector_interface.py
papermc_plugin_manager/console.py
papermc_plugin_manager/database.py
papermc_plugin_manager/exceptions.py
papermc_plugin_manager/logging.py
papermc_plugin_manager/plugin_manager.py
papermc_plugin_manager/utils.py
papermc_plugin_manager/connectors/__init__.py
papermc_plugin_manager/connectors/modrinth.py
papermc_plugin_manager/connectors/modrinth_models.py
papermc_plugin_manager-0.1.1.dist-info/METADATA
papermc_plugin_manager-0.1.1.dist-info/WHEEL
papermc_plugin_manager-0.1.1.dist-info/entry_points.txt
papermc_plugin_manager-0.1.1.dist-info/top_level.txt
papermc_plugin_manager-0.1.1.dist-info/RECORD
