Metadata-Version: 2.4
Name: papermc-plugin-manager
Version: 0.1.1
Summary: A modern CLI tool for managing PaperMC server plugins
Requires-Python: >=3.13
Requires-Dist: colorama>=0.4.6
Requires-Dist: logzero>=1.7.0
Requires-Dist: pydantic>=2.12.5
Requires-Dist: pyyaml>=6.0.3
Requires-Dist: requests>=2.32.5
Requires-Dist: rich>=14.2.0
Requires-Dist: semantic-version>=2.10.0
Requires-Dist: sqlalchemy>=2.0.45
Requires-Dist: typer>=0.20.0
